{
  "metric": {
    "__name__": "flink_taskmanager_job_task_Shuffle_Netty_Input_Buffers_inputQueueLength",
    "namespace": "flink",
    "service": "flink-taskmanager",
    "job": "flink-taskmanager",
    "instance": "[2001:cafe:42:3::98]:9249",
    "host": "_2001:cafe:42:3::98_",
    "pod": "flink-16000m-16384-0",
    "container": "taskmanager",
    "endpoint": "metrics",
    "job_id": "508692a0d68d8e6f1b9761f8a6c2b6d2",
    "job_name": "myjoin_transscale_0_0_1",
    "prometheus": "monitoring/prometheus-kube-prometheus-prometheus",
    "prometheus_replica": "prometheus-prometheus-kube-prometheus-prometheus-0",
    "subtask_index": "0",
    "task_attempt_id": "458e27873b16c79736a771c3501df8ff_32f0ffe0b6f0b990239bb81cec28b9d8_0_0",
    "task_attempt_num": "0",
    "task_id": "32f0ffe0b6f0b990239bb81cec28b9d8",
    "task_name": "TumblingEventTimeWindows____Timestamps_Watermarks",
    "tm_id": "_2001:cafe:42:3::98_:6122_da2d5a"
  },
  "values": [
    0,
    0,
    0,
    1,
    0,
    0,
    18,
    19,
    19,
    19,
    19,
    19,
    19,
    19,
    19,
    19,
    19,
    19,
    19,
    19,
    19,
    20,
    20,
    19,
    20,
    19,
    19,
    20,
    19,
    19,
    19,
    19,
    19,
    19,
    20,
    20,
    19,
    19,
    19,
    19,
    19,
    19,
    19,
    20,
    19,
    19,
    19,
    19,
    null
  ],
  "timestamps": [
    1737531535258,
    1737531540258,
    1737531545258,
    1737531550258,
    1737531555258,
    1737531560258,
    1737531565258,
    1737531570258,
    1737531575258,
    1737531580258,
    1737531585258,
    1737531590258,
    1737531595258,
    1737531600258,
    1737531605258,
    1737531610258,
    1737531615258,
    1737531620258,
    1737531625258,
    1737531630258,
    1737531635258,
    1737531640258,
    1737531645258,
    1737531650258,
    1737531655258,
    1737531660258,
    1737531665258,
    1737531670258,
    1737531675258,
    1737531680258,
    1737531685258,
    1737531690258,
    1737531695258,
    1737531700258,
    1737531705258,
    1737531710258,
    1737531715258,
    1737531720258,
    1737531725258,
    1737531730258,
    1737531735258,
    1737531740258,
    1737531745258,
    1737531750258,
    1737531755258,
    1737531760258,
    1737531765258,
    1737531770258,
    1737531775258
  ]
}
{
  "metric": {
    "__name__": "flink_taskmanager_job_task_Shuffle_Netty_Input_Buffers_inputQueueLength",
    "namespace": "flink",
    "service": "flink-taskmanager",
    "job": "flink-taskmanager",
    "instance": "[2001:cafe:42:3::98]:9249",
    "host": "_2001:cafe:42:3::98_",
    "pod": "flink-16000m-16384-0",
    "container": "taskmanager",
    "endpoint": "metrics",
    "job_id": "508692a0d68d8e6f1b9761f8a6c2b6d2",
    "job_name": "myjoin_transscale_0_0_1",
    "prometheus": "monitoring/prometheus-kube-prometheus-prometheus",
    "prometheus_replica": "prometheus-prometheus-kube-prometheus-prometheus-0",
    "subtask_index": "0",
    "task_attempt_id": "458e27873b16c79736a771c3501df8ff_31ec045e3401e87fc7879b43d8e8625d_0_0",
    "task_attempt_num": "0",
    "task_id": "31ec045e3401e87fc7879b43d8e8625d",
    "task_name": "Timestamps_Watermarks____Map",
    "tm_id": "_2001:cafe:42:3::98_:6122_da2d5a"
  },
  "values": [
    0,
    0,
    0,
    0,
    0,
    0,
    9,
    9,
    9,
    9,
    9,
    9,
    9,
    9,
    9,
    9,
    9,
    9,
    9,
    9,
    7,
    10,
    9,
    9,
    9,
    9,
    9,
    9,
    9,
    9,
    9,
    9,
    9,
    9,
    10,
    10,
    9,
    9,
    9,
    9,
    9,
    9,
    9,
    9,
    9,
    9,
    9,
    9,
    null
  ],
  "timestamps": [
    1737531535258,
    1737531540258,
    1737531545258,
    1737531550258,
    1737531555258,
    1737531560258,
    1737531565258,
    1737531570258,
    1737531575258,
    1737531580258,
    1737531585258,
    1737531590258,
    1737531595258,
    1737531600258,
    1737531605258,
    1737531610258,
    1737531615258,
    1737531620258,
    1737531625258,
    1737531630258,
    1737531635258,
    1737531640258,
    1737531645258,
    1737531650258,
    1737531655258,
    1737531660258,
    1737531665258,
    1737531670258,
    1737531675258,
    1737531680258,
    1737531685258,
    1737531690258,
    1737531695258,
    1737531700258,
    1737531705258,
    1737531710258,
    1737531715258,
    1737531720258,
    1737531725258,
    1737531730258,
    1737531735258,
    1737531740258,
    1737531745258,
    1737531750258,
    1737531755258,
    1737531760258,
    1737531765258,
    1737531770258,
    1737531775258
  ]
}
{
  "metric": {
    "__name__": "flink_taskmanager_job_task_Shuffle_Netty_Input_Buffers_inputQueueLength",
    "namespace": "flink",
    "service": "flink-taskmanager",
    "job": "flink-taskmanager",
    "instance": "[2001:cafe:42:3::98]:9249",
    "host": "_2001:cafe:42:3::98_",
    "pod": "flink-16000m-16384-0",
    "container": "taskmanager",
    "endpoint": "metrics",
    "job_id": "508692a0d68d8e6f1b9761f8a6c2b6d2",
    "job_name": "myjoin_transscale_0_0_1",
    "prometheus": "monitoring/prometheus-kube-prometheus-prometheus",
    "prometheus_replica": "prometheus-prometheus-kube-prometheus-prometheus-0",
    "subtask_index": "0",
    "task_attempt_id": "458e27873b16c79736a771c3501df8ff_e926317ddf99720773e3c7f4f412c3d7_0_0",
    "task_attempt_num": "0",
    "task_id": "e926317ddf99720773e3c7f4f412c3d7",
    "task_name": "Timestamps_Watermarks____Map",
    "tm_id": "_2001:cafe:42:3::98_:6122_da2d5a"
  },
  "values": [
    0,
    0,
    0,
    1,
    0,
    0,
    9,
    9,
    9,
    9,
    9,
    9,
    9,
    9,
    9,
    9,
    9,
    9,
    9,
    9,
    9,
    9,
    9,
    9,
    9,
    9,
    9,
    9,
    9,
    9,
    9,
    9,
    9,
    9,
    9,
    9,
    9,
    9,
    9,
    9,
    9,
    9,
    9,
    9,
    9,
    9,
    9,
    9,
    null
  ],
  "timestamps": [
    1737531535258,
    1737531540258,
    1737531545258,
    1737531550258,
    1737531555258,
    1737531560258,
    1737531565258,
    1737531570258,
    1737531575258,
    1737531580258,
    1737531585258,
    1737531590258,
    1737531595258,
    1737531600258,
    1737531605258,
    1737531610258,
    1737531615258,
    1737531620258,
    1737531625258,
    1737531630258,
    1737531635258,
    1737531640258,
    1737531645258,
    1737531650258,
    1737531655258,
    1737531660258,
    1737531665258,
    1737531670258,
    1737531675258,
    1737531680258,
    1737531685258,
    1737531690258,
    1737531695258,
    1737531700258,
    1737531705258,
    1737531710258,
    1737531715258,
    1737531720258,
    1737531725258,
    1737531730258,
    1737531735258,
    1737531740258,
    1737531745258,
    1737531750258,
    1737531755258,
    1737531760258,
    1737531765258,
    1737531770258,
    1737531775258
  ]
}
{
  "metric": {
    "__name__": "flink_taskmanager_job_task_Shuffle_Netty_Input_Buffers_inputQueueLength",
    "namespace": "flink",
    "service": "flink-taskmanager",
    "job": "flink-taskmanager",
    "instance": "[2001:cafe:42:3::98]:9249",
    "host": "_2001:cafe:42:3::98_",
    "pod": "flink-16000m-16384-0",
    "container": "taskmanager",
    "endpoint": "metrics",
    "job_id": "508692a0d68d8e6f1b9761f8a6c2b6d2",
    "job_name": "myjoin_transscale_0_0_1",
    "prometheus": "monitoring/prometheus-kube-prometheus-prometheus",
    "prometheus_replica": "prometheus-prometheus-kube-prometheus-prometheus-0",
    "subtask_index": "0",
    "task_attempt_id": "458e27873b16c79736a771c3501df8ff_41a95396e613c9f62f1da16142d5ddd2_0_0",
    "task_attempt_num": "0",
    "task_id": "41a95396e613c9f62f1da16142d5ddd2",
    "task_name": "Sink:_Sink",
    "tm_id": "_2001:cafe:42:3::98_:6122_da2d5a"
  },
  "values": [
    0,
    0,
    0,
    0,
    0,
    0,
    0,
    0,
    1,
    1,
    1,
    0,
    1,
    1,
    1,
    1,
    1,
    1,
    1,
    1,
    0,
    1,
    0,
    1,
    0,
    0,
    0,
    0,
    0,
    1,
    1,
    1,
    1,
    1,
    1,
    1,
    1,
    1,
    0,
    0,
    0,
    0,
    0,
    1,
    0,
    1,
    1,
    1,
    null
  ],
  "timestamps": [
    1737531535258,
    1737531540258,
    1737531545258,
    1737531550258,
    1737531555258,
    1737531560258,
    1737531565258,
    1737531570258,
    1737531575258,
    1737531580258,
    1737531585258,
    1737531590258,
    1737531595258,
    1737531600258,
    1737531605258,
    1737531610258,
    1737531615258,
    1737531620258,
    1737531625258,
    1737531630258,
    1737531635258,
    1737531640258,
    1737531645258,
    1737531650258,
    1737531655258,
    1737531660258,
    1737531665258,
    1737531670258,
    1737531675258,
    1737531680258,
    1737531685258,
    1737531690258,
    1737531695258,
    1737531700258,
    1737531705258,
    1737531710258,
    1737531715258,
    1737531720258,
    1737531725258,
    1737531730258,
    1737531735258,
    1737531740258,
    1737531745258,
    1737531750258,
    1737531755258,
    1737531760258,
    1737531765258,
    1737531770258,
    1737531775258
  ]
}
{
  "metric": {
    "__name__": "flink_taskmanager_job_task_Shuffle_Netty_Input_Buffers_inputQueueLength",
    "namespace": "flink",
    "service": "flink-taskmanager",
    "job": "flink-taskmanager",
    "instance": "[2001:cafe:42:3::98]:9249",
    "host": "_2001:cafe:42:3::98_",
    "pod": "flink-16000m-16384-0",
    "container": "taskmanager",
    "endpoint": "metrics",
    "job_id": "508692a0d68d8e6f1b9761f8a6c2b6d2",
    "job_name": "myjoin_transscale_0_0_1",
    "prometheus": "monitoring/prometheus-kube-prometheus-prometheus",
    "prometheus_replica": "prometheus-prometheus-kube-prometheus-prometheus-0",
    "subtask_index": "0",
    "task_attempt_id": "458e27873b16c79736a771c3501df8ff_9c7327831b3b5b4ae2c580979f474a9c_0_0",
    "task_attempt_num": "0",
    "task_id": "9c7327831b3b5b4ae2c580979f474a9c",
    "task_name": "Source:_Source2",
    "tm_id": "_2001:cafe:42:3::98_:6122_da2d5a"
  },
  "values": [
    0,
    0,
    0,
    0,
    0,
    0,
    0,
    0,
    0,
    0,
    0,
    0,
    0,
    0,
    0,
    0,
    0,
    0,
    0,
    0,
    0,
    0,
    0,
    0,
    0,
    0,
    0,
    0,
    0,
    0,
    0,
    0,
    0,
    0,
    0,
    0,
    0,
    0,
    0,
    0,
    0,
    0,
    0,
    0,
    0,
    0,
    0,
    0,
    null
  ],
  "timestamps": [
    1737531535258,
    1737531540258,
    1737531545258,
    1737531550258,
    1737531555258,
    1737531560258,
    1737531565258,
    1737531570258,
    1737531575258,
    1737531580258,
    1737531585258,
    1737531590258,
    1737531595258,
    1737531600258,
    1737531605258,
    1737531610258,
    1737531615258,
    1737531620258,
    1737531625258,
    1737531630258,
    1737531635258,
    1737531640258,
    1737531645258,
    1737531650258,
    1737531655258,
    1737531660258,
    1737531665258,
    1737531670258,
    1737531675258,
    1737531680258,
    1737531685258,
    1737531690258,
    1737531695258,
    1737531700258,
    1737531705258,
    1737531710258,
    1737531715258,
    1737531720258,
    1737531725258,
    1737531730258,
    1737531735258,
    1737531740258,
    1737531745258,
    1737531750258,
    1737531755258,
    1737531760258,
    1737531765258,
    1737531770258,
    1737531775258
  ]
}
{
  "metric": {
    "__name__": "flink_taskmanager_job_task_Shuffle_Netty_Input_Buffers_inputQueueLength",
    "namespace": "flink",
    "service": "flink-taskmanager",
    "job": "flink-taskmanager",
    "instance": "[2001:cafe:42:3::98]:9249",
    "host": "_2001:cafe:42:3::98_",
    "pod": "flink-16000m-16384-0",
    "container": "taskmanager",
    "endpoint": "metrics",
    "job_id": "508692a0d68d8e6f1b9761f8a6c2b6d2",
    "job_name": "myjoin_transscale_0_0_1",
    "prometheus": "monitoring/prometheus-kube-prometheus-prometheus",
    "prometheus_replica": "prometheus-prometheus-kube-prometheus-prometheus-0",
    "subtask_index": "0",
    "task_attempt_id": "458e27873b16c79736a771c3501df8ff_dca33db40b2f8f122636cd5297c0c511_0_0",
    "task_attempt_num": "0",
    "task_id": "dca33db40b2f8f122636cd5297c0c511",
    "task_name": "Source:_Source1",
    "tm_id": "_2001:cafe:42:3::98_:6122_da2d5a"
  },
  "values": [
    0,
    0,
    0,
    0,
    0,
    0,
    0,
    0,
    0,
    0,
    0,
    0,
    0,
    0,
    0,
    0,
    0,
    0,
    0,
    0,
    0,
    0,
    0,
    0,
    0,
    0,
    0,
    0,
    0,
    0,
    0,
    0,
    0,
    0,
    0,
    0,
    0,
    0,
    0,
    0,
    0,
    0,
    0,
    0,
    0,
    0,
    0,
    0,
    null
  ],
  "timestamps": [
    1737531535258,
    1737531540258,
    1737531545258,
    1737531550258,
    1737531555258,
    1737531560258,
    1737531565258,
    1737531570258,
    1737531575258,
    1737531580258,
    1737531585258,
    1737531590258,
    1737531595258,
    1737531600258,
    1737531605258,
    1737531610258,
    1737531615258,
    1737531620258,
    1737531625258,
    1737531630258,
    1737531635258,
    1737531640258,
    1737531645258,
    1737531650258,
    1737531655258,
    1737531660258,
    1737531665258,
    1737531670258,
    1737531675258,
    1737531680258,
    1737531685258,
    1737531690258,
    1737531695258,
    1737531700258,
    1737531705258,
    1737531710258,
    1737531715258,
    1737531720258,
    1737531725258,
    1737531730258,
    1737531735258,
    1737531740258,
    1737531745258,
    1737531750258,
    1737531755258,
    1737531760258,
    1737531765258,
    1737531770258,
    1737531775258
  ]
}
