{
  "metric": {
    "__name__": "flink_taskmanager_job_task_busyTimeMsPerSecond",
    "namespace": "flink",
    "service": "flink-taskmanager",
    "job": "flink-taskmanager",
    "instance": "[2001:cafe:42:4::1a]:9249",
    "host": "_2001:cafe:42:4::1a_",
    "pod": "flink-1000m-16384-0",
    "container": "taskmanager",
    "endpoint": "metrics",
    "job_id": "6e5a857f0aa6ab40414dc0d270c278b3",
    "job_name": "myjoin_transscale_0_0_1",
    "prometheus": "monitoring/prometheus-kube-prometheus-prometheus",
    "prometheus_replica": "prometheus-prometheus-kube-prometheus-prometheus-0",
    "subtask_index": "0",
    "task_attempt_id": "c02f091fa8a39ed9efc3723ec0adbd9d_31ec045e3401e87fc7879b43d8e8625d_0_0",
    "task_attempt_num": "0",
    "task_id": "31ec045e3401e87fc7879b43d8e8625d",
    "task_name": "Timestamps_Watermarks____Map",
    "tm_id": "_2001:cafe:42:4::1a_:6122_0af633"
  },
  "values": [
    1000,
    0,
    0,
    0,
    38,
    90,
    95,
    97,
    99,
    88,
    85,
    87,
    81,
    91,
    89,
    102,
    89,
    69,
    58,
    48,
    42,
    41,
    35,
    31,
    38,
    46,
    53,
    45,
    34,
    27,
    37,
    40,
    36,
    42,
    43,
    41,
    41,
    41,
    35,
    32,
    34,
    33,
    26,
    30,
    28,
    24,
    23,
    29,
    null
  ],
  "timestamps": [
    1737202993705,
    1737202998705,
    1737203003705,
    1737203008705,
    1737203013705,
    1737203018705,
    1737203023705,
    1737203028705,
    1737203033705,
    1737203038705,
    1737203043705,
    1737203048705,
    1737203053705,
    1737203058705,
    1737203063705,
    1737203068705,
    1737203073705,
    1737203078705,
    1737203083705,
    1737203088705,
    1737203093705,
    1737203098705,
    1737203103705,
    1737203108705,
    1737203113705,
    1737203118705,
    1737203123705,
    1737203128705,
    1737203133705,
    1737203138705,
    1737203143705,
    1737203148705,
    1737203153705,
    1737203158705,
    1737203163705,
    1737203168705,
    1737203173705,
    1737203178705,
    1737203183705,
    1737203188705,
    1737203193705,
    1737203198705,
    1737203203705,
    1737203208705,
    1737203213705,
    1737203218705,
    1737203223705,
    1737203228705,
    1737203233706
  ]
}
{
  "metric": {
    "__name__": "flink_taskmanager_job_task_busyTimeMsPerSecond",
    "namespace": "flink",
    "service": "flink-taskmanager",
    "job": "flink-taskmanager",
    "instance": "[2001:cafe:42:4::1a]:9249",
    "host": "_2001:cafe:42:4::1a_",
    "pod": "flink-1000m-16384-0",
    "container": "taskmanager",
    "endpoint": "metrics",
    "job_id": "6e5a857f0aa6ab40414dc0d270c278b3",
    "job_name": "myjoin_transscale_0_0_1",
    "prometheus": "monitoring/prometheus-kube-prometheus-prometheus",
    "prometheus_replica": "prometheus-prometheus-kube-prometheus-prometheus-0",
    "subtask_index": "0",
    "task_attempt_id": "c02f091fa8a39ed9efc3723ec0adbd9d_e926317ddf99720773e3c7f4f412c3d7_0_0",
    "task_attempt_num": "0",
    "task_id": "e926317ddf99720773e3c7f4f412c3d7",
    "task_name": "Timestamps_Watermarks____Map",
    "tm_id": "_2001:cafe:42:4::1a_:6122_0af633"
  },
  "values": [
    1000,
    0,
    0,
    0,
    0,
    40,
    50,
    53,
    64,
    58,
    63,
    66,
    62,
    70,
    69,
    78,
    79,
    63,
    52,
    43,
    31,
    31,
    18,
    13,
    18,
    30,
    37,
    31,
    23,
    17,
    32,
    39,
    38,
    42,
    44,
    47,
    48,
    43,
    38,
    33,
    37,
    35,
    24,
    28,
    26,
    21,
    21,
    26,
    null
  ],
  "timestamps": [
    1737202993705,
    1737202998705,
    1737203003705,
    1737203008705,
    1737203013705,
    1737203018705,
    1737203023705,
    1737203028705,
    1737203033705,
    1737203038705,
    1737203043705,
    1737203048705,
    1737203053705,
    1737203058705,
    1737203063705,
    1737203068705,
    1737203073705,
    1737203078705,
    1737203083705,
    1737203088705,
    1737203093705,
    1737203098705,
    1737203103705,
    1737203108705,
    1737203113705,
    1737203118705,
    1737203123705,
    1737203128705,
    1737203133705,
    1737203138705,
    1737203143705,
    1737203148705,
    1737203153705,
    1737203158705,
    1737203163705,
    1737203168705,
    1737203173705,
    1737203178705,
    1737203183705,
    1737203188705,
    1737203193705,
    1737203198705,
    1737203203705,
    1737203208705,
    1737203213705,
    1737203218705,
    1737203223705,
    1737203228705,
    1737203233706
  ]
}
{
  "metric": {
    "__name__": "flink_taskmanager_job_task_busyTimeMsPerSecond",
    "namespace": "flink",
    "service": "flink-taskmanager",
    "job": "flink-taskmanager",
    "instance": "[2001:cafe:42:4::1a]:9249",
    "host": "_2001:cafe:42:4::1a_",
    "pod": "flink-1000m-16384-0",
    "container": "taskmanager",
    "endpoint": "metrics",
    "job_id": "6e5a857f0aa6ab40414dc0d270c278b3",
    "job_name": "myjoin_transscale_0_0_1",
    "prometheus": "monitoring/prometheus-kube-prometheus-prometheus",
    "prometheus_replica": "prometheus-prometheus-kube-prometheus-prometheus-0",
    "subtask_index": "0",
    "task_attempt_id": "c02f091fa8a39ed9efc3723ec0adbd9d_32f0ffe0b6f0b990239bb81cec28b9d8_0_0",
    "task_attempt_num": "0",
    "task_id": "32f0ffe0b6f0b990239bb81cec28b9d8",
    "task_name": "TumblingEventTimeWindows____Timestamps_Watermarks",
    "tm_id": "_2001:cafe:42:4::1a_:6122_0af633"
  },
  "values": [
    1000,
    12,
    8,
    0,
    188,
    334,
    445,
    525,
    584,
    630,
    667,
    698,
    723,
    805,
    888,
    974,
    994,
    1000,
    1000,
    1000,
    1000,
    1000,
    1000,
    1000,
    1000,
    1000,
    1000,
    1000,
    1000,
    1000,
    1000,
    1000,
    1000,
    1000,
    1000,
    1000,
    1000,
    1000,
    1000,
    1000,
    1000,
    1000,
    1000,
    1000,
    1000,
    1000,
    1000,
    1000,
    null
  ],
  "timestamps": [
    1737202993705,
    1737202998705,
    1737203003705,
    1737203008705,
    1737203013705,
    1737203018705,
    1737203023705,
    1737203028705,
    1737203033705,
    1737203038705,
    1737203043705,
    1737203048705,
    1737203053705,
    1737203058705,
    1737203063705,
    1737203068705,
    1737203073705,
    1737203078705,
    1737203083705,
    1737203088705,
    1737203093705,
    1737203098705,
    1737203103705,
    1737203108705,
    1737203113705,
    1737203118705,
    1737203123705,
    1737203128705,
    1737203133705,
    1737203138705,
    1737203143705,
    1737203148705,
    1737203153705,
    1737203158705,
    1737203163705,
    1737203168705,
    1737203173705,
    1737203178705,
    1737203183705,
    1737203188705,
    1737203193705,
    1737203198705,
    1737203203705,
    1737203208705,
    1737203213705,
    1737203218705,
    1737203223705,
    1737203228705,
    1737203233706
  ]
}
{
  "metric": {
    "__name__": "flink_taskmanager_job_task_busyTimeMsPerSecond",
    "namespace": "flink",
    "service": "flink-taskmanager",
    "job": "flink-taskmanager",
    "instance": "[2001:cafe:42:4::1a]:9249",
    "host": "_2001:cafe:42:4::1a_",
    "pod": "flink-1000m-16384-0",
    "container": "taskmanager",
    "endpoint": "metrics",
    "job_id": "6e5a857f0aa6ab40414dc0d270c278b3",
    "job_name": "myjoin_transscale_0_0_1",
    "prometheus": "monitoring/prometheus-kube-prometheus-prometheus",
    "prometheus_replica": "prometheus-prometheus-kube-prometheus-prometheus-0",
    "subtask_index": "0",
    "task_attempt_id": "c02f091fa8a39ed9efc3723ec0adbd9d_41a95396e613c9f62f1da16142d5ddd2_0_0",
    "task_attempt_num": "0",
    "task_id": "41a95396e613c9f62f1da16142d5ddd2",
    "task_name": "Sink:_Sink",
    "tm_id": "_2001:cafe:42:4::1a_:6122_0af633"
  },
  "values": [
    1000,
    0,
    0,
    0,
    0,
    0,
    0,
    0,
    0,
    0,
    0,
    0,
    0,
    0,
    0,
    0,
    0,
    0,
    0,
    0,
    2,
    1,
    2,
    2,
    2,
    0,
    0,
    0,
    0,
    0,
    0,
    0,
    0,
    0,
    0,
    0,
    0,
    0,
    0,
    0,
    0,
    0,
    0,
    0,
    0,
    0,
    0,
    0,
    null
  ],
  "timestamps": [
    1737202993705,
    1737202998705,
    1737203003705,
    1737203008705,
    1737203013705,
    1737203018705,
    1737203023705,
    1737203028705,
    1737203033705,
    1737203038705,
    1737203043705,
    1737203048705,
    1737203053705,
    1737203058705,
    1737203063705,
    1737203068705,
    1737203073705,
    1737203078705,
    1737203083705,
    1737203088705,
    1737203093705,
    1737203098705,
    1737203103705,
    1737203108705,
    1737203113705,
    1737203118705,
    1737203123705,
    1737203128705,
    1737203133705,
    1737203138705,
    1737203143705,
    1737203148705,
    1737203153705,
    1737203158705,
    1737203163705,
    1737203168705,
    1737203173705,
    1737203178705,
    1737203183705,
    1737203188705,
    1737203193705,
    1737203198705,
    1737203203705,
    1737203208705,
    1737203213705,
    1737203218705,
    1737203223705,
    1737203228705,
    1737203233706
  ]
}
