{
  "metric": {
    "__name__": "flink_taskmanager_job_task_busyTimeMsPerSecond",
    "namespace": "flink",
    "service": "flink-taskmanager",
    "job": "flink-taskmanager",
    "instance": "[2001:cafe:42:4::33]:9249",
    "host": "_2001:cafe:42:4::33_",
    "pod": "flink-2000m-16384-0",
    "container": "taskmanager",
    "endpoint": "metrics",
    "job_id": "6d2ce80aee32498502b1255be971f722",
    "job_name": "myjoin_transscale_0_0_1",
    "prometheus": "monitoring/prometheus-kube-prometheus-prometheus",
    "prometheus_replica": "prometheus-prometheus-kube-prometheus-prometheus-0",
    "subtask_index": "0",
    "task_attempt_id": "79115e5e653705f4ba9289bf2de2edb6_32f0ffe0b6f0b990239bb81cec28b9d8_0_0",
    "task_attempt_num": "0",
    "task_id": "32f0ffe0b6f0b990239bb81cec28b9d8",
    "task_name": "TumblingEventTimeWindows____Timestamps_Watermarks",
    "tm_id": "_2001:cafe:42:4::33_:6122_817f77"
  },
  "values": [
    1000,
    399,
    440,
    291,
    414,
    531,
    609,
    665,
    707,
    740,
    766,
    787,
    805,
    855,
    898,
    982,
    1000,
    1000,
    1000,
    1000,
    1000,
    1000,
    1000,
    1000,
    1000,
    1000,
    1000,
    1000,
    1000,
    1000,
    1000,
    1000,
    1000,
    1000,
    1000,
    1000,
    1000,
    1000,
    1000,
    1000,
    1000,
    1000,
    1000,
    1000,
    1000,
    1000,
    1000,
    1000,
    null
  ],
  "timestamps": [
    1737213052896,
    1737213057896,
    1737213062896,
    1737213067896,
    1737213072896,
    1737213077896,
    1737213082896,
    1737213087896,
    1737213092896,
    1737213097896,
    1737213102896,
    1737213107896,
    1737213112896,
    1737213117896,
    1737213122896,
    1737213127896,
    1737213132896,
    1737213137896,
    1737213142896,
    1737213147896,
    1737213152896,
    1737213157896,
    1737213162896,
    1737213167896,
    1737213172896,
    1737213177896,
    1737213182896,
    1737213187896,
    1737213192896,
    1737213197896,
    1737213202896,
    1737213207896,
    1737213212896,
    1737213217896,
    1737213222896,
    1737213227896,
    1737213232896,
    1737213237896,
    1737213242896,
    1737213247896,
    1737213252896,
    1737213257896,
    1737213262896,
    1737213267896,
    1737213272896,
    1737213277896,
    1737213282896,
    1737213287896,
    1737213292897
  ]
}
{
  "metric": {
    "__name__": "flink_taskmanager_job_task_busyTimeMsPerSecond",
    "namespace": "flink",
    "service": "flink-taskmanager",
    "job": "flink-taskmanager",
    "instance": "[2001:cafe:42:4::33]:9249",
    "host": "_2001:cafe:42:4::33_",
    "pod": "flink-2000m-16384-0",
    "container": "taskmanager",
    "endpoint": "metrics",
    "job_id": "6d2ce80aee32498502b1255be971f722",
    "job_name": "myjoin_transscale_0_0_1",
    "prometheus": "monitoring/prometheus-kube-prometheus-prometheus",
    "prometheus_replica": "prometheus-prometheus-kube-prometheus-prometheus-0",
    "subtask_index": "0",
    "task_attempt_id": "79115e5e653705f4ba9289bf2de2edb6_41a95396e613c9f62f1da16142d5ddd2_0_0",
    "task_attempt_num": "0",
    "task_id": "41a95396e613c9f62f1da16142d5ddd2",
    "task_name": "Sink:_Sink",
    "tm_id": "_2001:cafe:42:4::33_:6122_817f77"
  },
  "values": [
    1000,
    166,
    84,
    48,
    32,
    26,
    22,
    17,
    17,
    16,
    15,
    16,
    17,
    3,
    4,
    6,
    7,
    8,
    9,
    11,
    11,
    10,
    10,
    9,
    7,
    7,
    4,
    6,
    7,
    6,
    7,
    7,
    7,
    5,
    3,
    4,
    4,
    5,
    8,
    7,
    7,
    6,
    7,
    7,
    6,
    9,
    10,
    9,
    null
  ],
  "timestamps": [
    1737213052896,
    1737213057896,
    1737213062896,
    1737213067896,
    1737213072896,
    1737213077896,
    1737213082896,
    1737213087896,
    1737213092896,
    1737213097896,
    1737213102896,
    1737213107896,
    1737213112896,
    1737213117896,
    1737213122896,
    1737213127896,
    1737213132896,
    1737213137896,
    1737213142896,
    1737213147896,
    1737213152896,
    1737213157896,
    1737213162896,
    1737213167896,
    1737213172896,
    1737213177896,
    1737213182896,
    1737213187896,
    1737213192896,
    1737213197896,
    1737213202896,
    1737213207896,
    1737213212896,
    1737213217896,
    1737213222896,
    1737213227896,
    1737213232896,
    1737213237896,
    1737213242896,
    1737213247896,
    1737213252896,
    1737213257896,
    1737213262896,
    1737213267896,
    1737213272896,
    1737213277896,
    1737213282896,
    1737213287896,
    1737213292897
  ]
}
{
  "metric": {
    "__name__": "flink_taskmanager_job_task_busyTimeMsPerSecond",
    "namespace": "flink",
    "service": "flink-taskmanager",
    "job": "flink-taskmanager",
    "instance": "[2001:cafe:42:4::33]:9249",
    "host": "_2001:cafe:42:4::33_",
    "pod": "flink-2000m-16384-0",
    "container": "taskmanager",
    "endpoint": "metrics",
    "job_id": "6d2ce80aee32498502b1255be971f722",
    "job_name": "myjoin_transscale_0_0_1",
    "prometheus": "monitoring/prometheus-kube-prometheus-prometheus",
    "prometheus_replica": "prometheus-prometheus-kube-prometheus-prometheus-0",
    "subtask_index": "0",
    "task_attempt_id": "79115e5e653705f4ba9289bf2de2edb6_31ec045e3401e87fc7879b43d8e8625d_0_0",
    "task_attempt_num": "0",
    "task_id": "31ec045e3401e87fc7879b43d8e8625d",
    "task_name": "Timestamps_Watermarks____Map",
    "tm_id": "_2001:cafe:42:4::33_:6122_817f77"
  },
  "values": [
    1000,
    221,
    117,
    77,
    98,
    88,
    95,
    82,
    71,
    68,
    64,
    57,
    50,
    35,
    34,
    32,
    20,
    13,
    4,
    2,
    2,
    0,
    0,
    1,
    3,
    0,
    1,
    3,
    4,
    4,
    2,
    5,
    5,
    10,
    6,
    3,
    3,
    3,
    2,
    5,
    0,
    3,
    2,
    4,
    8,
    0,
    1,
    4,
    null
  ],
  "timestamps": [
    1737213052896,
    1737213057896,
    1737213062896,
    1737213067896,
    1737213072896,
    1737213077896,
    1737213082896,
    1737213087896,
    1737213092896,
    1737213097896,
    1737213102896,
    1737213107896,
    1737213112896,
    1737213117896,
    1737213122896,
    1737213127896,
    1737213132896,
    1737213137896,
    1737213142896,
    1737213147896,
    1737213152896,
    1737213157896,
    1737213162896,
    1737213167896,
    1737213172896,
    1737213177896,
    1737213182896,
    1737213187896,
    1737213192896,
    1737213197896,
    1737213202896,
    1737213207896,
    1737213212896,
    1737213217896,
    1737213222896,
    1737213227896,
    1737213232896,
    1737213237896,
    1737213242896,
    1737213247896,
    1737213252896,
    1737213257896,
    1737213262896,
    1737213267896,
    1737213272896,
    1737213277896,
    1737213282896,
    1737213287896,
    1737213292897
  ]
}
{
  "metric": {
    "__name__": "flink_taskmanager_job_task_busyTimeMsPerSecond",
    "namespace": "flink",
    "service": "flink-taskmanager",
    "job": "flink-taskmanager",
    "instance": "[2001:cafe:42:4::33]:9249",
    "host": "_2001:cafe:42:4::33_",
    "pod": "flink-2000m-16384-0",
    "container": "taskmanager",
    "endpoint": "metrics",
    "job_id": "6d2ce80aee32498502b1255be971f722",
    "job_name": "myjoin_transscale_0_0_1",
    "prometheus": "monitoring/prometheus-kube-prometheus-prometheus",
    "prometheus_replica": "prometheus-prometheus-kube-prometheus-prometheus-0",
    "subtask_index": "0",
    "task_attempt_id": "79115e5e653705f4ba9289bf2de2edb6_e926317ddf99720773e3c7f4f412c3d7_0_0",
    "task_attempt_num": "0",
    "task_id": "e926317ddf99720773e3c7f4f412c3d7",
    "task_name": "Timestamps_Watermarks____Map",
    "tm_id": "_2001:cafe:42:4::33_:6122_817f77"
  },
  "values": [
    1000,
    194,
    110,
    72,
    81,
    75,
    91,
    78,
    67,
    72,
    68,
    60,
    53,
    43,
    41,
    38,
    29,
    23,
    12,
    11,
    11,
    0,
    0,
    1,
    3,
    0,
    0,
    0,
    0,
    1,
    0,
    1,
    1,
    7,
    6,
    4,
    7,
    4,
    3,
    7,
    5,
    9,
    5,
    3,
    5,
    1,
    0,
    2,
    null
  ],
  "timestamps": [
    1737213052896,
    1737213057896,
    1737213062896,
    1737213067896,
    1737213072896,
    1737213077896,
    1737213082896,
    1737213087896,
    1737213092896,
    1737213097896,
    1737213102896,
    1737213107896,
    1737213112896,
    1737213117896,
    1737213122896,
    1737213127896,
    1737213132896,
    1737213137896,
    1737213142896,
    1737213147896,
    1737213152896,
    1737213157896,
    1737213162896,
    1737213167896,
    1737213172896,
    1737213177896,
    1737213182896,
    1737213187896,
    1737213192896,
    1737213197896,
    1737213202896,
    1737213207896,
    1737213212896,
    1737213217896,
    1737213222896,
    1737213227896,
    1737213232896,
    1737213237896,
    1737213242896,
    1737213247896,
    1737213252896,
    1737213257896,
    1737213262896,
    1737213267896,
    1737213272896,
    1737213277896,
    1737213282896,
    1737213287896,
    1737213292897
  ]
}
